pauseonlock.py
pauseonlock-0.1.0.dist-info/LICENSE
pauseonlock-0.1.0.dist-info/METADATA
pauseonlock-0.1.0.dist-info/WHEEL
pauseonlock-0.1.0.dist-info/entry_points.txt
pauseonlock-0.1.0.dist-info/top_level.txt
pauseonlock-0.1.0.dist-info/RECORD
