Metadata-Version: 2.1
Name: pauseonlock
Version: 0.1.0
Summary: Pause/Resume your media players on screen locking/unlocking
Home-page: https://github.com/folixg/python-pauseonlock
Author: Thomas Goldbrunner
Author-email: thomas.goldbrunner@posteo.de
License: MIT
Project-URL: Bug Tracker, https://github.com/folixg/python-pauseonlock/issues
Platform: UNKNOWN
Classifier: Development Status :: 4 - Beta
Classifier: Intended Audience :: End Users/Desktop
Classifier: License :: OSI Approved :: MIT License
Classifier: Operating System :: POSIX :: Linux
Classifier: Programming Language :: Python :: 3 :: Only
Classifier: Programming Language :: Python :: 3.6
Classifier: Programming Language :: Python :: 3.7
Classifier: Programming Language :: Python :: 3.8
Classifier: Programming Language :: Python :: 3.9
Classifier: Programming Language :: Python :: 3.10
Classifier: Topic :: Desktop Environment :: Gnome
Classifier: Topic :: Desktop Environment :: K Desktop Environment (KDE)
Classifier: Topic :: Desktop Environment :: Screen Savers
Classifier: Topic :: Desktop Environment :: Window Managers :: XFCE
Classifier: Topic :: Multimedia
Classifier: Topic :: Multimedia :: Sound/Audio :: Players
Classifier: Topic :: Multimedia :: Video
Classifier: Topic :: Utilities
Requires-Python: >=3.6
Requires-Dist: dbus-next (>=0.2.2)
Provides-Extra: dev
Requires-Dist: pytest ; extra == 'dev'
Requires-Dist: black ; extra == 'dev'
Requires-Dist: flake8 ; extra == 'dev'
Requires-Dist: flake8-bugbear ; extra == 'dev'
Requires-Dist: pycodestyle ; extra == 'dev'
